aadraw/__init__.py
aadraw/draw.py
aadraw/utils.py
aadraw-0.0.3.dist-info/METADATA
aadraw-0.0.3.dist-info/WHEEL
aadraw-0.0.3.dist-info/top_level.txt
aadraw-0.0.3.dist-info/RECORD
